gxm/__init__.py
gxm/core.py
gxm/registration.py
gxm/typing.py
gxm/environments/__init__.py
gxm/environments/brax_environment.py
gxm/environments/craftax_environment.py
gxm/environments/envpool_environment.py
gxm/environments/gxm_environment.py
gxm/environments/gymnasium_environment.py
gxm/environments/gymnax_environment.py
gxm/environments/jaxatari_environmnet.py
gxm/environments/navix_environmnent.py
gxm/environments/pgx_environment.py
gxm/environments/xminigrid_environment.py
gxm/spaces/__init__.py
gxm/spaces/box.py
gxm/spaces/discrete.py
gxm/spaces/space.py
gxm/spaces/tree.py
gxm/utils/core.py
gxm/wrappers/__init__.py
gxm/wrappers/clip_reward.py
gxm/wrappers/discretize.py
gxm/wrappers/episode_counter.py
gxm/wrappers/episodic_life.py
gxm/wrappers/evaluate.py
gxm/wrappers/flatten_observation.py
gxm/wrappers/ignore_truncation.py
gxm/wrappers/record_episode_statistics.py
gxm/wrappers/rollout.py
gxm/wrappers/stack_observations.py
gxm/wrappers/step_counter.py
gxm/wrappers/sticky_action.py
gxm/wrappers/time_limit.py
gxm/wrappers/wrapper.py
gxm/wrappers/terminal/__init__.py
gxm/wrappers/terminal/gxm_to_gymnax.py
gxm/wrappers/terminal/gymnax_to_gxm.py
gxm-0.1.3.dist-info/licenses/LICENSE
gxm-0.1.3.dist-info/METADATA
gxm-0.1.3.dist-info/WHEEL
gxm-0.1.3.dist-info/top_level.txt
gxm-0.1.3.dist-info/RECORD
