Metadata-Version: 2.4
Name: gxm
Version: 0.1.3
Summary: Reinforcement Learning Environemts in JAX.
Author-email: huterguier <huterguier@gmail.com>
License-Expression: Apache-2.0
Project-URL: Homepage, https://github.com/huterguier/gxm
Classifier: Programming Language :: Python :: 3
Classifier: Operating System :: OS Independent
Requires-Python: >=3.10
License-File: LICENSE
Requires-Dist: jax>=0.5.0
Provides-Extra: dev
Requires-Dist: gxm[craftax,gymnasium,gymnax,navix]; extra == "dev"
Requires-Dist: black; extra == "dev"
Requires-Dist: isort; extra == "dev"
Requires-Dist: pytest; extra == "dev"
Requires-Dist: pytest-cov; extra == "dev"
Requires-Dist: tqdx; extra == "dev"
Provides-Extra: brax
Requires-Dist: brax>=0.13.0; extra == "brax"
Provides-Extra: gymnax
Requires-Dist: gymnax; extra == "gymnax"
Provides-Extra: gymnasium
Requires-Dist: gymnasium>=1.0.0; extra == "gymnasium"
Requires-Dist: ale-py; extra == "gymnasium"
Provides-Extra: envpool
Requires-Dist: envpool==0.6.6; extra == "envpool"
Requires-Dist: gym==0.23.1; extra == "envpool"
Requires-Dist: numpy<2; extra == "envpool"
Provides-Extra: pgx
Requires-Dist: pgx; extra == "pgx"
Provides-Extra: craftax
Requires-Dist: craftax; extra == "craftax"
Provides-Extra: navix
Requires-Dist: navix; extra == "navix"
Provides-Extra: xminigrid
Requires-Dist: xminigrid; extra == "xminigrid"
Dynamic: license-file
